{
  "id": "IMPL-026",
  "title": "Neutral Package Owner Review Seal",
  "status": "DONE_LOCAL_ONLY",
  "date": "2026-06-29",
  "scope": "docs/seal only",
  "neutralPackageExists": true,
  "manifestExists": true,
  "checksumsExist": true,
  "validationExists": true,
  "readmeExists": true,
  "outputExtension": ".uaos-neutral.json",
  "keyboardNative": false,
  "notPublicRelease": true,
  "notProduction": true,
  "realKeyboardCompatibility": "UNVERIFIED",
  "realKeyboardOutputCreated": false,
  "forbiddenKeyboardExtensionsCreated": false,
  "proprietarySamplesIncluded": false,
  "kontaktNativeInstrumentsContentIncluded": false,
  "publicUrlsCreated": false,
  "externalAutomationUsed": false,
  "outputs": [
    "uaos-ai-factory/implementation/reports/IMPL_026_NEUTRAL_PACKAGE_OWNER_REVIEW_SEAL_REPORT.md",
    "uaos-ai-factory/implementation/IMPL_026_NEUTRAL_PACKAGE_OWNER_REVIEW_SEAL_SUMMARY.json",
    "uaos-ai-factory/writer-sandbox/neutral-package-writer/outputs/owner-neutral-001/OWNER_REVIEW_SEAL.md",
    "uaos-ai-factory/writer-sandbox/neutral-package-writer/outputs/owner-neutral-001/NEXT_REAL_KEYBOARD_EXTENSION_GATE.md"
  ],
  "nextChoices": [
    "review neutral package content",
    "revise neutral metadata",
    "design real extension writer later",
    "stop before real keyboard output"
  ],
  "laterRealExtensionApprovalPhrase": "I approve experimental real keyboard-format output locally for owner testing only, with manifest, checksum, backup, no push, no deploy, no Vercel, no payment, no proprietary samples, and I accept the risk that the keyboard may reject the file.",
  "readyForOwnerReview": true,
  "readyForRealKeyboardOutputNow": false,
  "readyForExternalAutomation": false
}
