{
  "schema": "uaos-jobcenter-utf8-recovery-status-v1",
  "status": "PASS",
  "date": "2026-07-01",
  "npmEnoentFixed": true,
  "internalNpmCallsRemoved": true,
  "utf8SourceEnforced": true,
  "pdfRegenerated": true,
  "pptxRegenerated": true,
  "germanUmlautsPreserved": true,
  "mojibakeMarkersRemovedFromSourceStatusText": true,
  "jobcenterOnlyConfirmed": true,
  "linkMarkedNotLiveUntilUploadDeployApproval": true,
  "qaStatus": "PASS",
  "fixedGermanExamples": [
    "eigenständig",
    "gehören",
    "Prüfungen",
    "Für",
    "nächsten",
    "verlässliches",
    "benötigt",
    "Fähigkeit",
    "Präsentation",
    "Veröffentlichung",
    "öffentlich"
  ],
  "safety": {
    "localOnly": true,
    "push": false,
    "deploy": false,
    "vercel": false,
    "payment": false,
    "keyboardOutputCreated": false,
    "keyboardTransferAllowed": false,
    "appJsxTouched": false,
    "frontendSourceTouched": false
  }
}

